{
  "contact_id": "ctc_000022",
  "schema_version": "1.0.0",
  "created_at": "2026-07-08T17:03:12.756448+00:00",
  "updated_at": "2026-07-08T17:03:12.756448+00:00",
  "nombre": "Tatiana Guido Núñez",
  "empresa": "Walmart Connect México y Centroamérica",
  "cargo": "",
  "pais": "",
  "sector_raw": "",
  "stage": 3,
  "stage_texto": "Referido a Argerie Ramirez (Walmart)",
  "fecha": "06/07/26",
  "email": null,
  "sector_norm": "AMAZON_ECOMMERCE",
  "seniority": "DESCONOCIDO",
  "tiene_md": true,
  "conversation_id": "conv_000100",
  "historial_slug": "1783351274474"
}