{
  "schema_version": "1.0.0",
  "last_id": 541,
  "entries": {
    "sebastian-estevez": {
      "ctc_id": "ctc_000001"
    },
    "robinson-carrera-astudillo": {
      "ctc_id": "ctc_000002"
    },
    "ricardo-vargas-burgos": {
      "ctc_id": "ctc_000003"
    },
    "marta-saenz-herrera": {
      "ctc_id": "ctc_000004"
    },
    "marc-roca": {
      "ctc_id": "ctc_000005"
    },
    "laura-chacon-munoz": {
      "ctc_id": "ctc_000006"
    },
    "juanjo-pereira-seijo": {
      "ctc_id": "ctc_000007"
    },
    "jonathan-josafat-rivas-carvajal": {
      "ctc_id": "ctc_000008"
    },
    "ingrith-munoz-herrera": {
      "ctc_id": "ctc_000009"
    },
    "fabian-ignacio-corbalan-beltran": {
      "ctc_id": "ctc_000010"
    },
    "evin-tapia": {
      "ctc_id": "ctc_000011"
    },
    "diana-kuhlmann": {
      "ctc_id": "ctc_000012"
    },
    "allan-jimenez-monge": {
      "ctc_id": "ctc_000013"
    },
    "acelis-tunon-singh": {
      "ctc_id": "ctc_000014"
    },
    "1783352085248": {
      "ctc_id": "ctc_000015"
    },
    "1783351494857": {
      "ctc_id": "ctc_000016"
    },
    "1783351462818": {
      "ctc_id": "ctc_000017"
    },
    "1783351442066": {
      "ctc_id": "ctc_000018"
    },
    "1783351423592": {
      "ctc_id": "ctc_000019"
    },
    "1783351404452": {
      "ctc_id": "ctc_000020"
    },
    "1783351300760": {
      "ctc_id": "ctc_000021"
    },
    "1783351274474": {
      "ctc_id": "ctc_000022"
    },
    "1783351090478": {
      "ctc_id": "ctc_000023"
    },
    "1783351071179": {
      "ctc_id": "ctc_000024"
    },
    "1783351046537": {
      "ctc_id": "ctc_000025"
    },
    "1783351017460": {
      "ctc_id": "ctc_000026"
    },
    "1783350996366": {
      "ctc_id": "ctc_000027"
    },
    "1783350776312": {
      "ctc_id": "ctc_000028"
    },
    "1783350754458": {
      "ctc_id": "ctc_000029"
    },
    "1783350737274": {
      "ctc_id": "ctc_000030"
    },
    "1783350719240": {
      "ctc_id": "ctc_000031"
    },
    "1783350702555": {
      "ctc_id": "ctc_000032"
    },
    "1783350568569": {
      "ctc_id": "ctc_000033"
    },
    "1783350495803": {
      "ctc_id": "ctc_000034"
    },
    "1783350451421": {
      "ctc_id": "ctc_000035"
    },
    "1783350434263": {
      "ctc_id": "ctc_000036"
    },
    "1783350416533": {
      "ctc_id": "ctc_000037"
    },
    "1783350187433": {
      "ctc_id": "ctc_000038"
    },
    "1783350167783": {
      "ctc_id": "ctc_000039"
    },
    "1783350140234": {
      "ctc_id": "ctc_000040"
    },
    "1783350120218": {
      "ctc_id": "ctc_000041"
    },
    "1783350100199": {
      "ctc_id": "ctc_000042"
    },
    "1783349688787": {
      "ctc_id": "ctc_000043"
    },
    "1783349671419": {
      "ctc_id": "ctc_000044"
    },
    "1783349651559": {
      "ctc_id": "ctc_000045"
    },
    "1783349631642": {
      "ctc_id": "ctc_000046"
    },
    "1783349610268": {
      "ctc_id": "ctc_000047"
    },
    "1783349276055": {
      "ctc_id": "ctc_000048"
    },
    "1783349257050": {
      "ctc_id": "ctc_000049"
    },
    "1783349238065": {
      "ctc_id": "ctc_000050"
    },
    "1783349220271": {
      "ctc_id": "ctc_000051"
    },
    "1783349193882": {
      "ctc_id": "ctc_000052"
    },
    "1783348198376": {
      "ctc_id": "ctc_000053"
    },
    "1783348175345": {
      "ctc_id": "ctc_000054"
    },
    "1783348156031": {
      "ctc_id": "ctc_000055"
    },
    "1783348131141": {
      "ctc_id": "ctc_000056"
    },
    "1783348107030": {
      "ctc_id": "ctc_000057"
    },
    "1783347963204": {
      "ctc_id": "ctc_000058"
    },
    "1783347941775": {
      "ctc_id": "ctc_000059"
    },
    "1783347919045": {
      "ctc_id": "ctc_000060"
    },
    "1783347898757": {
      "ctc_id": "ctc_000061"
    },
    "1783347622225": {
      "ctc_id": "ctc_000062"
    },
    "1783347594046": {
      "ctc_id": "ctc_000063"
    },
    "1783347560836": {
      "ctc_id": "ctc_000064"
    },
    "1783347537214": {
      "ctc_id": "ctc_000065"
    },
    "1783347108088": {
      "ctc_id": "ctc_000066"
    },
    "1783345615754": {
      "ctc_id": "ctc_000067"
    },
    "1783345615753": {
      "ctc_id": "ctc_000068"
    },
    "1783345615752": {
      "ctc_id": "ctc_000069"
    },
    "1783029352313": {
      "ctc_id": "ctc_000070"
    },
    "1782951541279": {
      "ctc_id": "ctc_000071"
    },
    "1782951516217": {
      "ctc_id": "ctc_000072"
    },
    "1782951485997": {
      "ctc_id": "ctc_000073"
    },
    "1782951465225": {
      "ctc_id": "ctc_000074"
    },
    "1782951328687": {
      "ctc_id": "ctc_000075"
    },
    "1782951307313": {
      "ctc_id": "ctc_000076"
    },
    "1782951289396": {
      "ctc_id": "ctc_000077"
    },
    "1782951268395": {
      "ctc_id": "ctc_000078"
    },
    "1782951081079": {
      "ctc_id": "ctc_000079"
    },
    "1782951061927": {
      "ctc_id": "ctc_000080"
    },
    "1782951028477": {
      "ctc_id": "ctc_000081"
    },
    "1782951004437": {
      "ctc_id": "ctc_000082"
    },
    "1782950821439": {
      "ctc_id": "ctc_000083"
    },
    "1782950802778": {
      "ctc_id": "ctc_000084"
    },
    "1782950778363": {
      "ctc_id": "ctc_000085"
    },
    "1782950758955": {
      "ctc_id": "ctc_000086"
    },
    "1782950701386": {
      "ctc_id": "ctc_000087"
    },
    "1782950517071": {
      "ctc_id": "ctc_000088"
    },
    "1782950499659": {
      "ctc_id": "ctc_000089"
    },
    "1782950470107": {
      "ctc_id": "ctc_000090"
    },
    "1782950447246": {
      "ctc_id": "ctc_000091"
    },
    "1782950305262": {
      "ctc_id": "ctc_000092"
    },
    "1782950287901": {
      "ctc_id": "ctc_000093"
    },
    "1782950268650": {
      "ctc_id": "ctc_000094"
    },
    "1782950244403": {
      "ctc_id": "ctc_000095"
    },
    "1782931203579": {
      "ctc_id": "ctc_000096"
    },
    "1782931162915": {
      "ctc_id": "ctc_000097"
    },
    "1782931137509": {
      "ctc_id": "ctc_000098"
    },
    "1782931112159": {
      "ctc_id": "ctc_000099"
    },
    "1782930474472": {
      "ctc_id": "ctc_000100"
    },
    "1782930254133": {
      "ctc_id": "ctc_000101"
    },
    "1782930232078": {
      "ctc_id": "ctc_000102"
    },
    "1782930213815": {
      "ctc_id": "ctc_000103"
    },
    "1782930185583": {
      "ctc_id": "ctc_000104"
    },
    "1782930144723": {
      "ctc_id": "ctc_000105"
    },
    "1782929030427": {
      "ctc_id": "ctc_000106"
    },
    "1782929003415": {
      "ctc_id": "ctc_000107"
    },
    "1782928974837": {
      "ctc_id": "ctc_000108"
    },
    "1782928935189": {
      "ctc_id": "ctc_000109"
    },
    "1782928676973": {
      "ctc_id": "ctc_000110"
    },
    "1782928658963": {
      "ctc_id": "ctc_000111"
    },
    "1782928633723": {
      "ctc_id": "ctc_000112"
    },
    "1782928597669": {
      "ctc_id": "ctc_000113"
    },
    "1782577994349": {
      "ctc_id": "ctc_000114"
    },
    "1782405975778": {
      "ctc_id": "ctc_000115"
    },
    "1782405356701": {
      "ctc_id": "ctc_000116"
    },
    "1782405337746": {
      "ctc_id": "ctc_000117"
    },
    "1782405313046": {
      "ctc_id": "ctc_000118"
    },
    "1782405290456": {
      "ctc_id": "ctc_000119"
    },
    "1782405270044": {
      "ctc_id": "ctc_000120"
    },
    "1782139100292": {
      "ctc_id": "ctc_000121"
    },
    "1782138983964": {
      "ctc_id": "ctc_000122"
    },
    "1782138931767": {
      "ctc_id": "ctc_000123"
    },
    "1782138887892": {
      "ctc_id": "ctc_000124"
    },
    "1782138671430": {
      "ctc_id": "ctc_000125"
    },
    "1782138609481": {
      "ctc_id": "ctc_000126"
    },
    "1782138585474": {
      "ctc_id": "ctc_000127"
    },
    "1782138447215": {
      "ctc_id": "ctc_000128"
    },
    "1782138397522": {
      "ctc_id": "ctc_000129"
    },
    "1781886103549": {
      "ctc_id": "ctc_000130"
    },
    "1781883562159": {
      "ctc_id": "ctc_000131"
    },
    "1781883524781": {
      "ctc_id": "ctc_000132"
    },
    "1781883498883": {
      "ctc_id": "ctc_000133"
    },
    "1781883465913": {
      "ctc_id": "ctc_000134"
    },
    "1781883448601": {
      "ctc_id": "ctc_000135"
    },
    "1781883426341": {
      "ctc_id": "ctc_000136"
    },
    "1781883320025": {
      "ctc_id": "ctc_000137"
    },
    "1781883292919": {
      "ctc_id": "ctc_000138"
    },
    "1781883268749": {
      "ctc_id": "ctc_000139"
    },
    "1781882632364": {
      "ctc_id": "ctc_000140"
    },
    "1781828319026": {
      "ctc_id": "ctc_000141"
    },
    "1781828300282": {
      "ctc_id": "ctc_000142"
    },
    "1781828274721": {
      "ctc_id": "ctc_000143"
    },
    "1781828256207": {
      "ctc_id": "ctc_000144"
    },
    "1781828236686": {
      "ctc_id": "ctc_000145"
    },
    "1781828215092": {
      "ctc_id": "ctc_000146"
    },
    "1781828194091": {
      "ctc_id": "ctc_000147"
    },
    "1781828061827": {
      "ctc_id": "ctc_000148"
    },
    "1781828026435": {
      "ctc_id": "ctc_000149"
    },
    "1781828008582": {
      "ctc_id": "ctc_000150"
    },
    "1781827919012": {
      "ctc_id": "ctc_000151"
    },
    "1781827886324": {
      "ctc_id": "ctc_000152"
    },
    "1781827855742": {
      "ctc_id": "ctc_000153"
    },
    "1781827654593": {
      "ctc_id": "ctc_000154"
    },
    "1781827630576": {
      "ctc_id": "ctc_000155"
    },
    "1781827298903": {
      "ctc_id": "ctc_000156"
    },
    "1781827280686": {
      "ctc_id": "ctc_000157"
    },
    "1781827252163": {
      "ctc_id": "ctc_000158"
    },
    "1781826087569": {
      "ctc_id": "ctc_000159"
    },
    "1781826055737": {
      "ctc_id": "ctc_000160"
    },
    "1781826033893": {
      "ctc_id": "ctc_000161"
    },
    "1781825824091": {
      "ctc_id": "ctc_000162"
    },
    "1781825793517": {
      "ctc_id": "ctc_000163"
    },
    "1781825775098": {
      "ctc_id": "ctc_000164"
    },
    "1781824235935": {
      "ctc_id": "ctc_000165"
    },
    "1781824233461": {
      "ctc_id": "ctc_000166"
    },
    "1781824170234": {
      "ctc_id": "ctc_000167"
    },
    "1781824079410": {
      "ctc_id": "ctc_000168"
    },
    "1781824060265": {
      "ctc_id": "ctc_000169"
    },
    "1781824043209": {
      "ctc_id": "ctc_000170"
    },
    "1781823717099": {
      "ctc_id": "ctc_000171"
    },
    "1781823688738": {
      "ctc_id": "ctc_000172"
    },
    "1781823650675": {
      "ctc_id": "ctc_000173"
    },
    "1781823557593": {
      "ctc_id": "ctc_000174"
    },
    "1781823536824": {
      "ctc_id": "ctc_000175"
    },
    "1781823517234": {
      "ctc_id": "ctc_000176"
    },
    "1781823369965": {
      "ctc_id": "ctc_000177"
    },
    "1781823343086": {
      "ctc_id": "ctc_000178"
    },
    "1781823313227": {
      "ctc_id": "ctc_000179"
    },
    "1781823241973": {
      "ctc_id": "ctc_000180"
    },
    "1781823216049": {
      "ctc_id": "ctc_000181"
    },
    "1781823179614": {
      "ctc_id": "ctc_000182"
    },
    "1781823100633": {
      "ctc_id": "ctc_000183"
    },
    "1781823032050": {
      "ctc_id": "ctc_000184"
    },
    "1781822974509": {
      "ctc_id": "ctc_000185"
    },
    "1781822956392": {
      "ctc_id": "ctc_000186"
    },
    "1781822102850": {
      "ctc_id": "ctc_000187"
    },
    "1781822077960": {
      "ctc_id": "ctc_000188"
    },
    "1781822043634": {
      "ctc_id": "ctc_000189"
    },
    "1781821517208": {
      "ctc_id": "ctc_000190"
    },
    "1781821429104": {
      "ctc_id": "ctc_000191"
    },
    "1781821395422": {
      "ctc_id": "ctc_000192"
    },
    "1781821371275": {
      "ctc_id": "ctc_000193"
    },
    "1781821039676": {
      "ctc_id": "ctc_000194"
    },
    "1781821010424": {
      "ctc_id": "ctc_000195"
    },
    "1781820985340": {
      "ctc_id": "ctc_000196"
    },
    "1781820655568": {
      "ctc_id": "ctc_000197"
    },
    "1781820624842": {
      "ctc_id": "ctc_000198"
    },
    "1781820599929": {
      "ctc_id": "ctc_000199"
    },
    "1781820453978": {
      "ctc_id": "ctc_000200"
    },
    "1781820431776": {
      "ctc_id": "ctc_000201"
    },
    "1781820406196": {
      "ctc_id": "ctc_000202"
    },
    "1781818802404": {
      "ctc_id": "ctc_000203"
    },
    "1781806463714": {
      "ctc_id": "ctc_000204"
    },
    "1781806432529": {
      "ctc_id": "ctc_000205"
    },
    "1781806406422": {
      "ctc_id": "ctc_000206"
    },
    "1781805436586": {
      "ctc_id": "ctc_000207"
    },
    "1781805396914": {
      "ctc_id": "ctc_000208"
    },
    "1781805288566": {
      "ctc_id": "ctc_000209"
    },
    "1781805269802": {
      "ctc_id": "ctc_000210"
    },
    "1781804817868": {
      "ctc_id": "ctc_000211"
    },
    "1781804794367": {
      "ctc_id": "ctc_000212"
    },
    "1781804761084": {
      "ctc_id": "ctc_000213"
    },
    "1781804193469": {
      "ctc_id": "ctc_000214"
    },
    "1781804152692": {
      "ctc_id": "ctc_000215"
    },
    "1781804020482": {
      "ctc_id": "ctc_000216"
    },
    "1781803982114": {
      "ctc_id": "ctc_000217"
    },
    "1781803957955": {
      "ctc_id": "ctc_000218"
    },
    "1781803779660": {
      "ctc_id": "ctc_000219"
    },
    "1781803730058": {
      "ctc_id": "ctc_000220"
    },
    "1781803709254": {
      "ctc_id": "ctc_000221"
    },
    "1781803574540": {
      "ctc_id": "ctc_000222"
    },
    "1781801740779": {
      "ctc_id": "ctc_000223"
    },
    "1781801720560": {
      "ctc_id": "ctc_000224"
    },
    "1781801699247": {
      "ctc_id": "ctc_000225"
    },
    "1781801267629": {
      "ctc_id": "ctc_000226"
    },
    "1781801243063": {
      "ctc_id": "ctc_000227"
    },
    "1781801222043": {
      "ctc_id": "ctc_000228"
    },
    "1781800705485": {
      "ctc_id": "ctc_000229"
    },
    "1781800666611": {
      "ctc_id": "ctc_000230"
    },
    "1781800641804": {
      "ctc_id": "ctc_000231"
    },
    "1781800564039": {
      "ctc_id": "ctc_000232"
    },
    "1781800543681": {
      "ctc_id": "ctc_000233"
    },
    "1781800525000": {
      "ctc_id": "ctc_000234"
    },
    "1781800373108": {
      "ctc_id": "ctc_000235"
    },
    "1781800350347": {
      "ctc_id": "ctc_000236"
    },
    "1781800304526": {
      "ctc_id": "ctc_000237"
    },
    "1781800221165": {
      "ctc_id": "ctc_000238"
    },
    "1781800140312": {
      "ctc_id": "ctc_000239"
    },
    "1781799932010": {
      "ctc_id": "ctc_000240"
    },
    "1781799836074": {
      "ctc_id": "ctc_000241"
    },
    "1781799793632": {
      "ctc_id": "ctc_000242"
    },
    "1781796437841": {
      "ctc_id": "ctc_000243"
    },
    "1781796418817": {
      "ctc_id": "ctc_000244"
    },
    "1781796389715": {
      "ctc_id": "ctc_000245"
    },
    "1781740208618": {
      "ctc_id": "ctc_000246"
    },
    "1781554623897": {
      "ctc_id": "ctc_000247"
    },
    "1781303319181": {
      "ctc_id": "ctc_000248"
    },
    "1781303257171": {
      "ctc_id": "ctc_000249"
    },
    "1781303238560": {
      "ctc_id": "ctc_000250"
    },
    "1781303211532": {
      "ctc_id": "ctc_000251"
    },
    "1781303189335": {
      "ctc_id": "ctc_000252"
    },
    "1781303089474": {
      "ctc_id": "ctc_000253"
    },
    "1781303070962": {
      "ctc_id": "ctc_000254"
    },
    "1781303038650": {
      "ctc_id": "ctc_000255"
    },
    "1781302964015": {
      "ctc_id": "ctc_000256"
    },
    "1781302936557": {
      "ctc_id": "ctc_000257"
    },
    "1781302899798": {
      "ctc_id": "ctc_000258"
    },
    "1781302823408": {
      "ctc_id": "ctc_000259"
    },
    "1781302802463": {
      "ctc_id": "ctc_000260"
    },
    "1781302779651": {
      "ctc_id": "ctc_000261"
    },
    "1781302635292": {
      "ctc_id": "ctc_000262"
    },
    "1781302615607": {
      "ctc_id": "ctc_000263"
    },
    "1781302594342": {
      "ctc_id": "ctc_000264"
    },
    "1781302472728": {
      "ctc_id": "ctc_000265"
    },
    "1781302438756": {
      "ctc_id": "ctc_000266"
    },
    "1781302352889": {
      "ctc_id": "ctc_000267"
    },
    "1781302332245": {
      "ctc_id": "ctc_000268"
    },
    "1781302310219": {
      "ctc_id": "ctc_000269"
    },
    "1781301850027": {
      "ctc_id": "ctc_000270"
    },
    "1781301791456": {
      "ctc_id": "ctc_000271"
    },
    "1781301639175": {
      "ctc_id": "ctc_000272"
    },
    "1781301617748": {
      "ctc_id": "ctc_000273"
    },
    "1781301592824": {
      "ctc_id": "ctc_000274"
    },
    "1781300253282": {
      "ctc_id": "ctc_000275"
    },
    "1781300226742": {
      "ctc_id": "ctc_000276"
    },
    "1781300201655": {
      "ctc_id": "ctc_000277"
    },
    "1781300058525": {
      "ctc_id": "ctc_000278"
    },
    "1781300032665": {
      "ctc_id": "ctc_000279"
    },
    "1781300000001": {
      "ctc_id": "ctc_000280"
    },
    "1781299944641": {
      "ctc_id": "ctc_000281"
    },
    "1781299924395": {
      "ctc_id": "ctc_000282"
    },
    "1781299902762": {
      "ctc_id": "ctc_000283"
    },
    "1781299510065": {
      "ctc_id": "ctc_000284"
    },
    "1781299424872": {
      "ctc_id": "ctc_000285"
    },
    "1781299394395": {
      "ctc_id": "ctc_000286"
    },
    "1781298444499": {
      "ctc_id": "ctc_000287"
    },
    "1781298415376": {
      "ctc_id": "ctc_000288"
    },
    "1781298284542": {
      "ctc_id": "ctc_000289"
    },
    "1781298266459": {
      "ctc_id": "ctc_000290"
    },
    "1781298215868": {
      "ctc_id": "ctc_000291"
    },
    "1781298127652": {
      "ctc_id": "ctc_000292"
    },
    "1781298088583": {
      "ctc_id": "ctc_000293"
    },
    "1781298063070": {
      "ctc_id": "ctc_000294"
    },
    "1781297940409": {
      "ctc_id": "ctc_000295"
    },
    "1781297908099": {
      "ctc_id": "ctc_000296"
    },
    "1781297882963": {
      "ctc_id": "ctc_000297"
    },
    "1781281065838": {
      "ctc_id": "ctc_000298"
    },
    "1781280943779": {
      "ctc_id": "ctc_000299"
    },
    "1781280901195": {
      "ctc_id": "ctc_000300"
    },
    "1781280793685": {
      "ctc_id": "ctc_000301"
    },
    "1781280765425": {
      "ctc_id": "ctc_000302"
    },
    "1781280730601": {
      "ctc_id": "ctc_000303"
    },
    "1781280134553": {
      "ctc_id": "ctc_000304"
    },
    "1781280112220": {
      "ctc_id": "ctc_000305"
    },
    "1781280086480": {
      "ctc_id": "ctc_000306"
    },
    "1781279978015": {
      "ctc_id": "ctc_000307"
    },
    "1781279945364": {
      "ctc_id": "ctc_000308"
    },
    "1781279898423": {
      "ctc_id": "ctc_000309"
    },
    "1781279792635": {
      "ctc_id": "ctc_000310"
    },
    "1781279773035": {
      "ctc_id": "ctc_000311"
    },
    "1781279735601": {
      "ctc_id": "ctc_000312"
    },
    "1781279241341": {
      "ctc_id": "ctc_000313"
    },
    "1781278824767": {
      "ctc_id": "ctc_000314"
    },
    "1781278560594": {
      "ctc_id": "ctc_000315"
    },
    "1781278541679": {
      "ctc_id": "ctc_000316"
    },
    "1781278506060": {
      "ctc_id": "ctc_000317"
    },
    "1781278386599": {
      "ctc_id": "ctc_000318"
    },
    "1781278351245": {
      "ctc_id": "ctc_000319"
    },
    "1781278322120": {
      "ctc_id": "ctc_000320"
    },
    "1781278170747": {
      "ctc_id": "ctc_000321"
    },
    "1781278143545": {
      "ctc_id": "ctc_000322"
    },
    "1781277691183": {
      "ctc_id": "ctc_000323"
    },
    "1781277655431": {
      "ctc_id": "ctc_000324"
    },
    "1781277632346": {
      "ctc_id": "ctc_000325"
    },
    "1781277544204": {
      "ctc_id": "ctc_000326"
    },
    "1781277518665": {
      "ctc_id": "ctc_000327"
    },
    "1781277479810": {
      "ctc_id": "ctc_000328"
    },
    "1781277397154": {
      "ctc_id": "ctc_000329"
    },
    "1781277376410": {
      "ctc_id": "ctc_000330"
    },
    "1781277352294": {
      "ctc_id": "ctc_000331"
    },
    "1781277270217": {
      "ctc_id": "ctc_000332"
    },
    "1781277249242": {
      "ctc_id": "ctc_000333"
    },
    "1781277204907": {
      "ctc_id": "ctc_000334"
    },
    "1781277102243": {
      "ctc_id": "ctc_000335"
    },
    "1781277059175": {
      "ctc_id": "ctc_000336"
    },
    "1781277035743": {
      "ctc_id": "ctc_000337"
    },
    "1781276722501": {
      "ctc_id": "ctc_000338"
    },
    "1781276715171": {
      "ctc_id": "ctc_000339"
    },
    "1781276680298": {
      "ctc_id": "ctc_000340"
    },
    "1781275401736": {
      "ctc_id": "ctc_000341"
    },
    "1781274703674": {
      "ctc_id": "ctc_000342"
    },
    "1781131274724": {
      "ctc_id": "ctc_000343"
    },
    "1781131111734": {
      "ctc_id": "ctc_000344"
    },
    "1781131026032": {
      "ctc_id": "ctc_000345"
    },
    "1781130842424": {
      "ctc_id": "ctc_000346"
    },
    "1781130815606": {
      "ctc_id": "ctc_000347"
    },
    "1781129811472": {
      "ctc_id": "ctc_000348"
    },
    "1781129713826": {
      "ctc_id": "ctc_000349"
    },
    "1781129686916": {
      "ctc_id": "ctc_000350"
    },
    "1781129582138": {
      "ctc_id": "ctc_000351"
    },
    "1781129554034": {
      "ctc_id": "ctc_000352"
    },
    "1781129513646": {
      "ctc_id": "ctc_000353"
    },
    "1781129376690": {
      "ctc_id": "ctc_000354"
    },
    "1781129348242": {
      "ctc_id": "ctc_000355"
    },
    "1781129302593": {
      "ctc_id": "ctc_000356"
    },
    "1781114410294": {
      "ctc_id": "ctc_000357"
    },
    "1781114380392": {
      "ctc_id": "ctc_000358"
    },
    "1781114350238": {
      "ctc_id": "ctc_000359"
    },
    "1781114269618": {
      "ctc_id": "ctc_000360"
    },
    "1781114246038": {
      "ctc_id": "ctc_000361"
    },
    "1781114218181": {
      "ctc_id": "ctc_000362"
    },
    "1781114079850": {
      "ctc_id": "ctc_000363"
    },
    "1781114052274": {
      "ctc_id": "ctc_000364"
    },
    "1781113995514": {
      "ctc_id": "ctc_000365"
    },
    "1781113906277": {
      "ctc_id": "ctc_000366"
    },
    "1781113868288": {
      "ctc_id": "ctc_000367"
    },
    "1781113829207": {
      "ctc_id": "ctc_000368"
    },
    "1781113513522": {
      "ctc_id": "ctc_000369"
    },
    "1781113481665": {
      "ctc_id": "ctc_000370"
    },
    "1781113457948": {
      "ctc_id": "ctc_000371"
    },
    "1781113296315": {
      "ctc_id": "ctc_000372"
    },
    "1781113244219": {
      "ctc_id": "ctc_000373"
    },
    "1781113211016": {
      "ctc_id": "ctc_000374"
    },
    "1781113105180": {
      "ctc_id": "ctc_000375"
    },
    "1781113068126": {
      "ctc_id": "ctc_000376"
    },
    "1781113043722": {
      "ctc_id": "ctc_000377"
    },
    "1781112924765": {
      "ctc_id": "ctc_000378"
    },
    "1781112885103": {
      "ctc_id": "ctc_000379"
    },
    "1781112809881": {
      "ctc_id": "ctc_000380"
    },
    "1781112696901": {
      "ctc_id": "ctc_000381"
    },
    "1781112674702": {
      "ctc_id": "ctc_000382"
    },
    "1781112648274": {
      "ctc_id": "ctc_000383"
    },
    "1781112540471": {
      "ctc_id": "ctc_000384"
    },
    "1781112495043": {
      "ctc_id": "ctc_000385"
    },
    "1781112442582": {
      "ctc_id": "ctc_000386"
    },
    "1781112247534": {
      "ctc_id": "ctc_000387"
    },
    "1781112205383": {
      "ctc_id": "ctc_000388"
    },
    "1781112173539": {
      "ctc_id": "ctc_000389"
    },
    "1781040232667": {
      "ctc_id": "ctc_000390"
    },
    "1781040147959": {
      "ctc_id": "ctc_000391"
    },
    "1781040117527": {
      "ctc_id": "ctc_000392"
    },
    "1781038399234": {
      "ctc_id": "ctc_000393"
    },
    "1781038303150": {
      "ctc_id": "ctc_000394"
    },
    "1781038125219": {
      "ctc_id": "ctc_000395"
    },
    "1781037605390": {
      "ctc_id": "ctc_000396"
    },
    "1781037539466": {
      "ctc_id": "ctc_000397"
    },
    "1781037505798": {
      "ctc_id": "ctc_000398"
    },
    "1781036858090": {
      "ctc_id": "ctc_000399"
    },
    "1781036825238": {
      "ctc_id": "ctc_000400"
    },
    "1781036764170": {
      "ctc_id": "ctc_000401"
    },
    "1781036527620": {
      "ctc_id": "ctc_000402"
    },
    "1781036456558": {
      "ctc_id": "ctc_000403"
    },
    "1781036214660": {
      "ctc_id": "ctc_000404"
    },
    "1781026904266": {
      "ctc_id": "ctc_000405"
    },
    "1781026808234": {
      "ctc_id": "ctc_000406"
    },
    "1781026611010": {
      "ctc_id": "ctc_000407"
    },
    "1781026483953": {
      "ctc_id": "ctc_000408"
    },
    "1781026397381": {
      "ctc_id": "ctc_000409"
    },
    "1780960000005": {
      "ctc_id": "ctc_000410"
    },
    "1780960000004": {
      "ctc_id": "ctc_000411"
    },
    "1780960000003": {
      "ctc_id": "ctc_000412"
    },
    "1780960000001": {
      "ctc_id": "ctc_000413"
    },
    "1780953617763": {
      "ctc_id": "ctc_000414"
    },
    "1780953315531": {
      "ctc_id": "ctc_000415"
    },
    "1780951919738": {
      "ctc_id": "ctc_000416"
    },
    "1780951429799": {
      "ctc_id": "ctc_000417"
    },
    "1780951299259": {
      "ctc_id": "ctc_000418"
    },
    "1780950962750": {
      "ctc_id": "ctc_000419"
    },
    "1780950903863": {
      "ctc_id": "ctc_000420"
    },
    "1780950831909": {
      "ctc_id": "ctc_000421"
    },
    "1780949947998": {
      "ctc_id": "ctc_000422"
    },
    "1780949911750": {
      "ctc_id": "ctc_000423"
    },
    "1780946717065": {
      "ctc_id": "ctc_000424"
    },
    "1780946688358": {
      "ctc_id": "ctc_000425"
    },
    "1780946651464": {
      "ctc_id": "ctc_000426"
    },
    "1780946551573": {
      "ctc_id": "ctc_000427"
    },
    "1780946523711": {
      "ctc_id": "ctc_000428"
    },
    "1780946496347": {
      "ctc_id": "ctc_000429"
    },
    "1780946391012": {
      "ctc_id": "ctc_000430"
    },
    "1780946343025": {
      "ctc_id": "ctc_000431"
    },
    "1780946309754": {
      "ctc_id": "ctc_000432"
    },
    "1780946213885": {
      "ctc_id": "ctc_000433"
    },
    "1780946166815": {
      "ctc_id": "ctc_000434"
    },
    "1780946128994": {
      "ctc_id": "ctc_000435"
    },
    "1780945956729": {
      "ctc_id": "ctc_000436"
    },
    "1780945933057": {
      "ctc_id": "ctc_000437"
    },
    "1780945839007": {
      "ctc_id": "ctc_000438"
    },
    "1780945645229": {
      "ctc_id": "ctc_000439"
    },
    "1780945613370": {
      "ctc_id": "ctc_000440"
    },
    "1780945577142": {
      "ctc_id": "ctc_000441"
    },
    "1780943748029": {
      "ctc_id": "ctc_000442"
    },
    "1780943712655": {
      "ctc_id": "ctc_000443"
    },
    "1780943666979": {
      "ctc_id": "ctc_000444"
    },
    "1780943492162": {
      "ctc_id": "ctc_000445"
    },
    "1780943454309": {
      "ctc_id": "ctc_000446"
    },
    "1780943307600": {
      "ctc_id": "ctc_000447"
    },
    "1780943215527": {
      "ctc_id": "ctc_000448"
    },
    "1780943142426": {
      "ctc_id": "ctc_000449"
    },
    "1780942861997": {
      "ctc_id": "ctc_000450"
    },
    "1780942811324": {
      "ctc_id": "ctc_000451"
    },
    "1780942600023": {
      "ctc_id": "ctc_000452"
    },
    "1780942503797": {
      "ctc_id": "ctc_000453"
    },
    "1780940712587": {
      "ctc_id": "ctc_000454"
    },
    "1780940650353": {
      "ctc_id": "ctc_000455"
    },
    "1780940377517": {
      "ctc_id": "ctc_000456"
    },
    "1780940106609": {
      "ctc_id": "ctc_000457"
    },
    "1780940083084": {
      "ctc_id": "ctc_000458"
    },
    "1780940041785": {
      "ctc_id": "ctc_000459"
    },
    "1780939927467": {
      "ctc_id": "ctc_000460"
    },
    "1780939492298": {
      "ctc_id": "ctc_000461"
    },
    "1780939461362": {
      "ctc_id": "ctc_000462"
    },
    "1780939392775": {
      "ctc_id": "ctc_000463"
    },
    "1780939284624": {
      "ctc_id": "ctc_000464"
    },
    "1780939218197": {
      "ctc_id": "ctc_000465"
    },
    "1780939122119": {
      "ctc_id": "ctc_000466"
    },
    "1780937549394": {
      "ctc_id": "ctc_000467"
    },
    "1780937203910": {
      "ctc_id": "ctc_000468"
    },
    "1780936425525": {
      "ctc_id": "ctc_000469"
    },
    "1780935462722": {
      "ctc_id": "ctc_000470"
    },
    "1780934975992": {
      "ctc_id": "ctc_000471"
    },
    "1780934238114": {
      "ctc_id": "ctc_000472"
    },
    "1780933381653": {
      "ctc_id": "ctc_000473"
    },
    "1780668386256": {
      "ctc_id": "ctc_000474"
    },
    "1780668196050": {
      "ctc_id": "ctc_000475"
    },
    "1780668157446": {
      "ctc_id": "ctc_000476"
    },
    "1780668117920": {
      "ctc_id": "ctc_000477"
    },
    "1780668081426": {
      "ctc_id": "ctc_000478"
    },
    "1780667982726": {
      "ctc_id": "ctc_000479"
    },
    "1780667959327": {
      "ctc_id": "ctc_000480"
    },
    "1780667942196": {
      "ctc_id": "ctc_000481"
    },
    "1780667639230": {
      "ctc_id": "ctc_000482"
    },
    "1780666743717": {
      "ctc_id": "ctc_000483"
    },
    "1780666664201": {
      "ctc_id": "ctc_000484"
    },
    "1780666602171": {
      "ctc_id": "ctc_000485"
    },
    "1780666509134": {
      "ctc_id": "ctc_000486"
    },
    "1780666351585": {
      "ctc_id": "ctc_000487"
    },
    "1780666322583": {
      "ctc_id": "ctc_000488"
    },
    "1780666291357": {
      "ctc_id": "ctc_000489"
    },
    "1780666263236": {
      "ctc_id": "ctc_000490"
    },
    "1780665547834": {
      "ctc_id": "ctc_000491"
    },
    "1780665466844": {
      "ctc_id": "ctc_000492"
    },
    "1780665390097": {
      "ctc_id": "ctc_000493"
    },
    "1780665326658": {
      "ctc_id": "ctc_000494"
    },
    "1780607923010": {
      "ctc_id": "ctc_000495"
    },
    "1780607891050": {
      "ctc_id": "ctc_000496"
    },
    "1780607501225": {
      "ctc_id": "ctc_000497"
    },
    "1780607462705": {
      "ctc_id": "ctc_000498"
    },
    "1780607408383": {
      "ctc_id": "ctc_000499"
    },
    "1780605693132": {
      "ctc_id": "ctc_000500"
    },
    "1780605692132": {
      "ctc_id": "ctc_000501"
    },
    "1780605691132": {
      "ctc_id": "ctc_000502"
    },
    "1780605690132": {
      "ctc_id": "ctc_000503"
    },
    "1780605689132": {
      "ctc_id": "ctc_000504"
    },
    "1780605688132": {
      "ctc_id": "ctc_000505"
    },
    "1780605687132": {
      "ctc_id": "ctc_000506"
    },
    "1780605686132": {
      "ctc_id": "ctc_000507"
    },
    "1780604881457": {
      "ctc_id": "ctc_000508"
    },
    "1780604509703": {
      "ctc_id": "ctc_000509"
    },
    "1780604374723": {
      "ctc_id": "ctc_000510"
    },
    "1780604308873": {
      "ctc_id": "ctc_000511"
    },
    "1780603159177": {
      "ctc_id": "ctc_000512"
    },
    "1780591292696": {
      "ctc_id": "ctc_000513"
    },
    "1780590947454": {
      "ctc_id": "ctc_000514"
    },
    "1780590475668": {
      "ctc_id": "ctc_000515"
    },
    "1780588296685": {
      "ctc_id": "ctc_000516"
    },
    "1750025000001": {
      "ctc_id": "ctc_000517"
    },
    "1749498000000": {
      "ctc_id": "ctc_000518"
    },
    "1749467400000": {
      "ctc_id": "ctc_000519"
    },
    "1749400000001": {
      "ctc_id": "ctc_000520"
    },
    "1749390000001": {
      "ctc_id": "ctc_000521"
    },
    "1749380300007": {
      "ctc_id": "ctc_000522"
    },
    "1749380300006": {
      "ctc_id": "ctc_000523"
    },
    "1749380300005": {
      "ctc_id": "ctc_000524"
    },
    "1749380300004": {
      "ctc_id": "ctc_000525"
    },
    "1749380300003": {
      "ctc_id": "ctc_000526"
    },
    "1749380300002": {
      "ctc_id": "ctc_000527"
    },
    "1749380300001": {
      "ctc_id": "ctc_000528"
    },
    "1749380200002": {
      "ctc_id": "ctc_000529"
    },
    "1749380100002": {
      "ctc_id": "ctc_000530"
    },
    "1749380100001": {
      "ctc_id": "ctc_000531"
    },
    "1749380000009": {
      "ctc_id": "ctc_000532"
    },
    "1749380000008": {
      "ctc_id": "ctc_000533"
    },
    "1749380000007": {
      "ctc_id": "ctc_000534"
    },
    "1749380000006": {
      "ctc_id": "ctc_000535"
    },
    "1749380000005": {
      "ctc_id": "ctc_000536"
    },
    "1749380000004": {
      "ctc_id": "ctc_000537"
    },
    "1749380000003": {
      "ctc_id": "ctc_000538"
    },
    "1749380000002": {
      "ctc_id": "ctc_000539"
    },
    "1749380000001": {
      "ctc_id": "ctc_000540"
    },
    "1783350100200": {
      "ctc_id": "ctc_000541"
    }
  }
}